[
    { "h2": "Управление с телефона", "p": "Для удобства наших клиентов мы разработали первое в Казахстане мобильное приложение «Тревожная кнопка». Защитить себя, своих близких и свое имущество стало еще проще. Оказавшись в сложной, угрожающей жизни ситуации, одним касанием пальца вы активируете мобильный отряд оперативного реагирования" },
    { "h2": "", "p" : ""},
    { "h2": "", "p" : ""},
    { "h2": "", "p" : ""},
    { "h2": "", "p" : ""},
    { "h2": "", "p" : ""},
    { "h2": "", "p" : ""},
    { "h2": "", "p" : ""},
    { "h2": "", "p" : ""}

]